{
  "name": "OTP",
  "nodes": [
    {
      "parameters": {
        "httpMethod": "POST",
        "path": "Email",
        "options": {}
      },
      "id": "455fc4b5-08f5-469a-9616-d4f4afe5bd34",
      "name": "Webhook",
      "type": "n8n-nodes-base.webhook",
      "typeVersion": 1,
      "position": [
        -368,
        64
      ],
      "webhookId": "e8906125-8ab1-47fb-aad8-56dd2ce2bc98"
    },
    {
      "parameters": {
        "sendTo": "={{ $j$('Webhook').item.json.body.otpson.body.email }}",
        "subject": "🎉 Account Approved! Welcome to AOTMS LMS",
        "message": "WellCome To Aotms Grab Your Carreer Here",
        "options": {}
      },
      "id": "996f51b8-1590-4584-b682-865f27eda72a",
      "name": "Send Approval Email",
      "type": "n8n-nodes-base.gmail",
      "typeVersion": 2,
      "position": [
        336,
        208
      ],
      "webhookId": "75dcf1cf-f8c9-43c0-9edf-5f67578b4f3f",
      "credentials": {
        "gmailOAuth2": {
          "id": "pPqZBHxow1vqfa4g",
          "name": "Gmail account 2"
        }
      }
    },
    {
      "parameters": {
        "sendTo": "={{ $json.body.email }}",
        "subject": "=🎉 Account Approved! Welcome to AOTMS LMS                  {{ $json.body.event }}",
        "message": "=Name: {{ $json.body.full_name }}\n\nYour OTP is: {{ $json.body.otp }}\n\nPlease use this OTP to verify your account.\n\nThis OTP is valid for 2 minutes.\n",
        "options": {}
      },
      "type": "n8n-nodes-base.gmail",
      "typeVersion": 2.2,
      "position": [
        336,
        -32
      ],
      "id": "a9ece990-62d4-4799-9202-7f5e46464a77",
      "name": "Send a message",
      "webhookId": "5d1080f6-9fc4-4081-8e31-59ef8c8f3eda",
      "credentials": {
        "gmailOAuth2": {
          "id": "pPqZBHxow1vqfa4g",
          "name": "Gmail account 2"
        }
      }
    },
    {
      "parameters": {
        "dataType": "string",
        "value1": "={{ $json.body.event }}",
        "rules": {
          "rules": [
            {
              "value2": "otp_verification",
              "output": 1
            },
            {
              "value2": "user_approved",
              "output": 2
            }
          ]
        }
      },
      "id": "173fd654-7597-49e3-b506-81b4e0a4fc6c",
      "name": "Switch Event",
      "type": "n8n-nodes-base.switch",
      "typeVersion": 1,
      "position": [
        -48,
        48
      ]
    }
  ],
  "pinData": {},
  "connections": {
    "Webhook": {
      "main": [
        [
          {
            "node": "Switch Event",
            "type": "main",
            "index": 0
          }
        ]
      ]
    },
    "Switch Event": {
      "main": [
        [],
        [
          {
            "node": "Send a message",
            "type": "main",
            "index": 0
          }
        ],
        [
          {
            "node": "Send Approval Email",
            "type": "main",
            "index": 0
          }
        ]
      ]
    }
  },
  "active": false,
  "settings": {
    "executionOrder": "v1",
    "binaryMode": "separate",
    "availableInMCP": false
  },
  "versionId": "65094abe-5eab-4be1-98a2-fd7762f3da6f",
  "meta": {
    "templateCredsSetupCompleted": true,
    "instanceId": "ac53766b75ba98327cb8367953362c144cd1e7b33149a3b252d1556380af54e8"
  },
  "id": "NolWqDkj6JSFxqiQ",
  "tags": []
}